drugbank_downloader/__init__.py
drugbank_downloader/__main__.py
drugbank_downloader/api.py
drugbank_downloader/cli.py
drugbank_downloader/py.typed
drugbank_downloader/version.py
drugbank_downloader-0.2.0.dist-info/LICENSE
drugbank_downloader-0.2.0.dist-info/METADATA
drugbank_downloader-0.2.0.dist-info/WHEEL
drugbank_downloader-0.2.0.dist-info/entry_points.txt
drugbank_downloader-0.2.0.dist-info/top_level.txt
drugbank_downloader-0.2.0.dist-info/RECORD
