Metadata-Version: 2.1
Name: drugbank_downloader
Version: 0.2.0
Summary: A tool for reproducibly downloading and extracting DrugBank data
Author-email: Charles Tapley Hoyt <cthoyt@gmail.com>
Maintainer-email: Charles Tapley Hoyt <cthoyt@gmail.com>
License: MIT License
Project-URL: Bug Tracker, https://github.com/cthoyt/drugbank-downloader/issues
Project-URL: Homepage, https://github.com/cthoyt/drugbank-downloader
Project-URL: Repository, https://github.com/cthoyt/drugbank-downloader.git
Project-URL: Documentation, https://drugbank_downloader.readthedocs.io
Keywords: snekpack,cookiecutter
Classifier: Development Status :: 1 - Planning
Classifier: Environment :: Console
Classifier: Intended Audience :: Developers
Classifier: License :: OSI Approved :: MIT License
Classifier: Operating System :: OS Independent
Classifier: Framework :: Pytest
Classifier: Framework :: tox
Classifier: Framework :: Sphinx
Classifier: Programming Language :: Python
Classifier: Programming Language :: Python :: 3.9
Classifier: Programming Language :: Python :: 3.10
Classifier: Programming Language :: Python :: 3.11
Classifier: Programming Language :: Python :: 3.12
Classifier: Programming Language :: Python :: 3 :: Only
Requires-Python: >=3.9
License-File: LICENSE
Requires-Dist: pystow
Requires-Dist: click
Requires-Dist: more_click
Requires-Dist: bioversions
Requires-Dist: lxml
Provides-Extra: tests
Requires-Dist: pytest; extra == "tests"
Requires-Dist: coverage; extra == "tests"
Provides-Extra: docs
Requires-Dist: sphinx<8; extra == "docs"
Requires-Dist: sphinx-rtd-theme; extra == "docs"
Requires-Dist: sphinx-click; extra == "docs"
Requires-Dist: sphinx_automodapi; extra == "docs"
